{
  "display": {
    "icon": {
      "item": "perodiumcraft:hochiym"
    },
    "title": {
      "translate": "advancements.stack_hochiym.title"
    },
    "description": {
      "translate": "advancements.stack_hochiym.descr"
    },
    "frame": "task",
    "show_toast": true,
    "announce_to_chat": true,
    "hidden": false
  },
  "criteria": {
    "stack_hochiym": {
      "trigger": "minecraft:inventory_changed",
      "conditions": {
        "items": [
          {
            "items": [
              "perodiumcraft:hochiym"
            ],
            "count": {
              "min": 64,
              "max": 64
            }
          }
        ]
      }
    }
  },
  "parent": "perodiumcraft:test"
}