{
  "_fv": 24,
  "_type": "gui",
  "definition": {
    "type": 0,
    "width": 176,
    "height": 166,
    "inventoryOffsetX": 0,
    "inventoryOffsetY": 0,
    "renderBgLayer": false,
    "doesPauseGame": false,
    "components": [
      {
        "type": "image",
        "data": {
          "image": "guibackground.png",
          "use1Xscale": false,
          "name": "guibackground.png",
          "x": 96,
          "y": 62
        }
      },
      {
        "type": "label",
        "data": {
          "text": "Perodium Ingot",
          "color": {
            "value": -13421773,
            "falpha": 0.0
          },
          "name": "Perodium Ingot",
          "x": 177,
          "y": 71
        }
      },
      {
        "type": "image",
        "data": {
          "image": "iron_block.png",
          "use1Xscale": false,
          "name": "iron_block.png",
          "x": 168,
          "y": 98
        }
      },
      {
        "type": "image",
        "data": {
          "image": "diamond_block.png",
          "use1Xscale": false,
          "name": "diamond_block.png",
          "x": 204,
          "y": 98
        }
      },
      {
        "type": "image",
        "data": {
          "image": "netherite_block.png",
          "use1Xscale": false,
          "name": "netherite_block.png",
          "x": 186,
          "y": 116
        }
      },
      {
        "type": "image",
        "data": {
          "image": "emerald_block.png",
          "use1Xscale": false,
          "name": "emerald_block.png",
          "x": 168,
          "y": 134
        }
      },
      {
        "type": "image",
        "data": {
          "image": "gold_block.png",
          "use1Xscale": false,
          "name": "gold_block.png",
          "x": 204,
          "y": 134
        }
      },
      {
        "type": "image",
        "data": {
          "image": "nochiymblock.png",
          "use1Xscale": false,
          "name": "nochiymblock.png",
          "x": 186,
          "y": 98
        }
      },
      {
        "type": "image",
        "data": {
          "image": "akvamarineblock.png",
          "use1Xscale": false,
          "name": "akvamarineblock.png",
          "x": 168,
          "y": 116
        }
      },
      {
        "type": "image",
        "data": {
          "image": "rubyblock.png",
          "use1Xscale": false,
          "name": "rubyblock.png",
          "x": 204,
          "y": 116
        }
      },
      {
        "type": "image",
        "data": {
          "image": "infinitiblock.png",
          "use1Xscale": false,
          "name": "infinitiblock.png",
          "x": 186,
          "y": 134
        }
      },
      {
        "type": "image",
        "data": {
          "image": "guideravno.png",
          "use1Xscale": false,
          "name": "guideravno.png",
          "x": 222,
          "y": 116
        }
      },
      {
        "type": "image",
        "data": {
          "image": "perodiumingot.png",
          "use1Xscale": false,
          "name": "perodiumingot.png",
          "x": 240,
          "y": 116
        }
      },
      {
        "type": "label",
        "data": {
          "text": "2",
          "color": {
            "value": -13421773,
            "falpha": 0.0
          },
          "name": "2",
          "x": 251,
          "y": 127
        }
      },
      {
        "type": "button",
        "data": {
          "text": "<",
          "onClick": {
            "name": "GuideProcedure"
          },
          "width": 30,
          "height": 20,
          "name": "<",
          "x": 177,
          "y": 152
        }
      },
      {
        "type": "button",
        "data": {
          "text": ">",
          "onClick": {
            "name": "GuideProcedure"
          },
          "width": 30,
          "height": 20,
          "name": ">",
          "x": 213,
          "y": 152
        }
      }
    ],
    "gridSettings": {
      "sx": 18,
      "sy": 18,
      "ox": 11,
      "oy": 15,
      "snapOnGrid": true
    }
  }
}